boardfarm3_docsis/__init__.py
boardfarm3_docsis/exceptions.py
boardfarm3_docsis/py.typed
boardfarm3_docsis/configs/__init__.py
boardfarm3_docsis/configs/mibs/CL-PKTC-EUE-DEV-MIB.txt
boardfarm3_docsis/configs/mibs/CL-PKTC-EUE-EDVA-MIB.txt
boardfarm3_docsis/configs/mibs/CL-PKTC-EUE-RST-MIB.txt
boardfarm3_docsis/configs/mibs/CL-PKTC-EUE-TC-MIB.txt
boardfarm3_docsis/configs/mibs/CL-PKTC-EUE-USER-MIB.txt
boardfarm3_docsis/configs/mibs/CLAB-ANI-DEV-MIB.mib
boardfarm3_docsis/configs/mibs/CLAB-ANI-NID-MIB.mib
boardfarm3_docsis/configs/mibs/CLAB-DEF-MIB-2017-04-13.mib
boardfarm3_docsis/configs/mibs/CLAB-DNS-MIB.mib
boardfarm3_docsis/configs/mibs/CLAB-GRE-MIB.mib
boardfarm3_docsis/configs/mibs/CLAB-GW-MIB-2016-08-04.mib
boardfarm3_docsis/configs/mibs/CLAB-GW-MIB.mib
boardfarm3_docsis/configs/mibs/CLAB-TOPO-MIB.mib
boardfarm3_docsis/configs/mibs/CLAB-UPS-MIB.mib
boardfarm3_docsis/configs/mibs/CLAB-WIFI-MIB.mib
boardfarm3_docsis/configs/mibs/DIFFSERV-DSCP-TC.mib
boardfarm3_docsis/configs/mibs/DIFFSERV-MIB.mib
boardfarm3_docsis/configs/mibs/DOCS-BPI-MIB.mib
boardfarm3_docsis/configs/mibs/DOCS-BPI2-MIB.mib
boardfarm3_docsis/configs/mibs/DOCS-BPI2EXT-MIB-2017-04-13.mib
boardfarm3_docsis/configs/mibs/DOCS-CABLE-DEVICE-MIB.mib
boardfarm3_docsis/configs/mibs/DOCS-CABLE-DEVICE-TRAP-MIB.mib
boardfarm3_docsis/configs/mibs/DOCS-DIAG-MIB.mib
boardfarm3_docsis/configs/mibs/DOCS-DRF-MIB.mib
boardfarm3_docsis/configs/mibs/DOCS-IETF-BPI2-MIB.mib
boardfarm3_docsis/configs/mibs/DOCS-IF-EXT-MIB.mib
boardfarm3_docsis/configs/mibs/DOCS-IF-MIB.mib
boardfarm3_docsis/configs/mibs/DOCS-IF3-MIB-2019-05-16.txt
boardfarm3_docsis/configs/mibs/DOCS-IF3-MIB.mib
boardfarm3_docsis/configs/mibs/DOCS-IF31-MIB-2018-11-15.mib
boardfarm3_docsis/configs/mibs/DOCS-IF31-MIB-2019-05-16.txt
boardfarm3_docsis/configs/mibs/DOCS-IF31-MIB.mib
boardfarm3_docsis/configs/mibs/DOCS-IFEXT2-MIB-2011-06-23.mib
boardfarm3_docsis/configs/mibs/DOCS-LOADBAL3-MIB.mib
boardfarm3_docsis/configs/mibs/DOCS-MCAST-AUTH-MIB.mib
boardfarm3_docsis-1.0.1.dist-info/entry_points.txt
boardfarm3_docsis-1.0.1.dist-info/licenses/LICENSE
boardfarm3_docsis-1.0.1.dist-info/WHEEL
boardfarm3_docsis-1.0.1.dist-info/METADATA
boardfarm3_docsis-1.0.1.dist-info/RECORD
