Metadata-Version: 2.4
Name: boardfarm3_docsis
Version: 1.0.1
Summary: An add-on to boardfarm that contains DOCSIS specific libraries.
Author-email: Various <t&iconnectivityboardfarm@libertyglobal.com>
Requires-Python: >=3.9
Classifier: Intended Audience :: Developers
Classifier: Intended Audience :: Information Technology
Classifier: Intended Audience :: Telecommunications Industry
Classifier: License :: OSI Approved :: BSD License
Classifier: Programming Language :: Python :: 3
Classifier: Topic :: Software Development :: Embedded Systems
Classifier: Topic :: Software Development :: Quality Assurance
Classifier: Topic :: Software Development :: Testing
Classifier: Topic :: Software Development :: Testing :: Acceptance
License-File: LICENSE
Requires-Dist: boardfarm3>=1.0.0
Requires-Dist: pandas
Requires-Dist: pexpect
Requires-Dist: termcolor
Requires-Dist: pytest-boardfarm3 ; extra == "demo-test"
Requires-Dist: darglint2==v1.8.2 ; extra == "dev"
Requires-Dist: flake8 ; extra == "dev"
Requires-Dist: flake8-bugbear ; extra == "dev"
Requires-Dist: flake8-builtins ; extra == "dev"
Requires-Dist: flake8-comprehensions ; extra == "dev"
Requires-Dist: flake8-docstrings ; extra == "dev"
Requires-Dist: flake8-rst ; extra == "dev"
Requires-Dist: flake8-rst-docstrings ; extra == "dev"
Requires-Dist: mypy ; extra == "dev"
Requires-Dist: nox ; extra == "dev"
Requires-Dist: pre-commit ; extra == "dev"
Requires-Dist: pylint ; extra == "dev"
Requires-Dist: ruff==v0.11.5 ; extra == "dev"
Requires-Dist: sphinx ; extra == "doc"
Requires-Dist: pytest ; extra == "test"
Requires-Dist: pytest-cov ; extra == "test"
Requires-Dist: pytest-mock ; extra == "test"
Requires-Dist: pytest-randomly ; extra == "test"
Project-URL: Source, https://github.com/lgirdk/boardfarm-docsis
Provides-Extra: demo-test
Provides-Extra: dev
Provides-Extra: doc
Provides-Extra: test
